flake8_no_print/__init__.py
flake8_no_print/meta.py
flake8_no_print/plugin.py
flake8_no_print-0.1.1.dist-info/LICENSE.md
flake8_no_print-0.1.1.dist-info/METADATA
flake8_no_print-0.1.1.dist-info/WHEEL
flake8_no_print-0.1.1.dist-info/entry_points.txt
flake8_no_print-0.1.1.dist-info/top_level.txt
flake8_no_print-0.1.1.dist-info/RECORD
